{
  "file": "BumpChart11.svg",
  "cvd_type": "deutan",
  "status": "recolored",
  "phases": {
    "phase1": {
      "n_data_elements": 27,
      "n_legend_elements": 0,
      "n_nondata_elements": 17,
      "n_data_colors": 26,
      "original_palette": [
        "#d88b8b",
        "#c1aa87",
        "#bf9269",
        "#bfa769",
        "#efdd3a",
        "#aebf69",
        "#e2714d",
        "#b0d19f",
        "#70bf69",
        "#69bf77",
        "#b8d6e8",
        "#69bfa0",
        "#ddb757",
        "#69b4bf",
        "#69a0bf",
        "#698bbf",
        "#6977bf",
        "#7069bf",
        "#8469bf",
        "#9969bf",
        "#af3c19",
        "#bf69bb",
        "#bf69a7",
        "#bf6992",
        "#bf697e",
        "#cccccc"
      ],
      "legend_luminance_monotonic": true,
      "n_legend_swatches_ordered": 0
    },
    "phase2": {
      "palette_type": "sequential",
      "confidence": 0.85,
      "details": {
        "n_colors": 26,
        "lightness_range": 45.30485824645857,
        "is_monotonic": false,
        "monotonic_direction": "non-monotonic",
        "is_v_shaped": false,
        "v_midpoint_index": -1,
        "hue_diversity_deg": 115.42140548909403,
        "has_hue_clusters": false,
        "n_achromatic": 2,
        "avg_chroma": 40.34745183746337,
        "rule": "1: large_palette_sequential"
      }
    },
    "phase3": {
      "n_categories": 26,
      "has_numeric_labels": true,
      "has_string_labels": true,
      "usage_distribution": "uniform",
      "has_semantic_midpoint": false,
      "midpoint_type": null,
      "possible_mismatch": false
    },
    "phase4": {
      "needs_user_choice": false,
      "reconciled_type": "sequential",
      "mismatch_explanation": null
    },
    "phase5": {
      "tests_run": [
        {
          "name": "Sequential Test 1: Monotonicity",
          "passed": false,
          "value": 0.0,
          "threshold": 1.0,
          "repair_suggestion": "Force monotonic L* (Single-hue ramp or adjust L*)"
        },
        {
          "name": "Sequential Test 2: Uniformity",
          "passed": false,
          "value": 0.73,
          "threshold": 0.51,
          "repair_suggestion": "Redistribute L* evenly (Clip range or resample steps)"
        },
        {
          "name": "Sequential Test 3: Direction",
          "passed": true,
          "value": 1.0,
          "threshold": 1.0,
          "repair_suggestion": null
        },
        {
          "name": "Sequential Test 4: Min Step Size",
          "passed": false,
          "value": 0.26,
          "threshold": 1.32,
          "repair_suggestion": "Expand L* range or reduce number of bins"
        },
        {
          "name": "Sequential Cross-Check: Adjacent \u0394E",
          "passed": false,
          "value": 0.43,
          "threshold": 1.32,
          "repair_suggestion": "Multi-hue ramp has plateau under CVD. Remap to single-hue CVD-safe ramp (viridis, cividis) or increase L* separation."
        }
      ],
      "all_tests_passed": false
    },
    "phase6": {
      "color_mapping": {
        "#7069bf": "#08306b",
        "#8469bf": "#093978",
        "#9969bf": "#094286",
        "#bf69bb": "#084c94",
        "#6977bf": "#0c559f",
        "#bf69a7": "#155ea6",
        "#698bbf": "#1b67ad",
        "#bf6992": "#2070b4",
        "#bf697e": "#2b79b9",
        "#69a0bf": "#3482be",
        "#d88b8b": "#3c8bc3",
        "#b8d6e8": "#4694c7",
        "#69b4bf": "#529ccc",
        "#cccccc": "#5da4d0",
        "#af3c19": "#68acd5",
        "#e2714d": "#76b4d8",
        "#bf9269": "#85bbdb",
        "#c1aa87": "#92c3de",
        "#69bfa0": "#a0cbe2",
        "#bfa769": "#abcfe5",
        "#b0d19f": "#b6d4e9",
        "#ddb757": "#c1d9ed",
        "#69bf77": "#cee0f2",
        "#aebf69": "#dce9f6",
        "#70bf69": "#e9f2fb",
        "#efdd3a": "#f7fbff"
      },
      "new_palette": [
        "#3c8bc3",
        "#92c3de",
        "#85bbdb",
        "#abcfe5",
        "#f7fbff",
        "#dce9f6",
        "#76b4d8",
        "#b6d4e9",
        "#e9f2fb",
        "#cee0f2",
        "#4694c7",
        "#a0cbe2",
        "#c1d9ed",
        "#529ccc",
        "#3482be",
        "#1b67ad",
        "#0c559f",
        "#08306b",
        "#093978",
        "#094286",
        "#68acd5",
        "#084c94",
        "#155ea6",
        "#2070b4",
        "#2b79b9",
        "#5da4d0"
      ],
      "verification_tests": [
        {
          "name": "Sequential Test 1: Monotonicity",
          "passed": true,
          "value": 1.0
        },
        {
          "name": "Sequential Test 2: Uniformity",
          "passed": true,
          "value": 0.13
        },
        {
          "name": "Sequential Test 3: Direction",
          "passed": true,
          "value": 1.0
        },
        {
          "name": "Sequential Test 4: Min Step Size",
          "passed": true,
          "value": 2.15
        }
      ],
      "verification_passed": true,
      "iterations_used": 1,
      "iteration_log": [
        {
          "iteration": 1,
          "color_mapping": {
            "#7069bf": "#08306b",
            "#8469bf": "#093978",
            "#9969bf": "#094286",
            "#bf69bb": "#084c94",
            "#6977bf": "#0c559f",
            "#bf69a7": "#155ea6",
            "#698bbf": "#1b67ad",
            "#bf6992": "#2070b4",
            "#bf697e": "#2b79b9",
            "#69a0bf": "#3482be",
            "#d88b8b": "#3c8bc3",
            "#b8d6e8": "#4694c7",
            "#69b4bf": "#529ccc",
            "#cccccc": "#5da4d0",
            "#af3c19": "#68acd5",
            "#e2714d": "#76b4d8",
            "#bf9269": "#85bbdb",
            "#c1aa87": "#92c3de",
            "#69bfa0": "#a0cbe2",
            "#bfa769": "#abcfe5",
            "#b0d19f": "#b6d4e9",
            "#ddb757": "#c1d9ed",
            "#69bf77": "#cee0f2",
            "#aebf69": "#dce9f6",
            "#70bf69": "#e9f2fb",
            "#efdd3a": "#f7fbff"
          },
          "verification_passed": true,
          "tests": [
            {
              "name": "Sequential Test 1: Monotonicity",
              "passed": true,
              "value": 1.0
            },
            {
              "name": "Sequential Test 2: Uniformity",
              "passed": true,
              "value": 0.13
            },
            {
              "name": "Sequential Test 3: Direction",
              "passed": true,
              "value": 1.0
            },
            {
              "name": "Sequential Test 4: Min Step Size",
              "passed": true,
              "value": 2.15
            }
          ]
        }
      ]
    }
  },
  "warnings": [],
  "recoloring_applied": true,
  "processing_time_sec": 0.019
}