{
  "file": "Heatmap21.svg",
  "cvd_type": "deutan",
  "status": "recolored",
  "phases": {
    "phase1": {
      "n_data_elements": 601,
      "n_legend_elements": 0,
      "n_nondata_elements": 17,
      "n_data_colors": 117,
      "original_palette": [
        "#a5c5f1",
        "#dae4ff",
        "#e6efff",
        "#cfddfd",
        "#edf5ff",
        "#b4cdf6",
        "#c9d8fb",
        "#ebf3ff",
        "#ccdbfc",
        "#d5e2fe",
        "#a9c7f3",
        "#adc8f5",
        "#82abec",
        "#5b8ee2",
        "#c6d6fb",
        "#c2d4fa",
        "#95b8ef",
        "#f6fbff",
        "#d1defe",
        "#6f9fe9",
        "#6c9ce8",
        "#77a4ea",
        "#6293e5",
        "#376bd5",
        "#9dbef0",
        "#4c82de",
        "#dce6ff",
        "#1948c4",
        "#3c72d7",
        "#87afed",
        "#b7cff7",
        "#cad8fb",
        "#ccdbfb",
        "#ceddfd",
        "#e0eaff",
        "#6999e6",
        "#a1c2f0",
        "#7ea8eb",
        "#6596e6",
        "#b0cbf5",
        "#dee8ff",
        "#e9f0ff",
        "#99bbef",
        "#bbd1f8",
        "#d7e3ff",
        "#e3ecff",
        "#f1f7ff",
        "#f4faff",
        "#dbe6ff",
        "#eff6ff",
        "#e4edff",
        "#d3dffe",
        "#75a1ea",
        "#8bb2ed",
        "#90b5ee",
        "#e2ebff",
        "#2c5fd1",
        "#578ae1",
        "#77a3ea",
        "#3a6ed6",
        "#bed2f9",
        "#b2cbf5",
        "#5084df",
        "#7aa7ea",
        "#3f76da",
        "#c3d5fa",
        "#6696e6",
        "#f7fcff",
        "#447bdc",
        "#487fdd",
        "#f6faff",
        "#8ab0ed",
        "#d5e1ff",
        "#1b4bc5",
        "#5387e0",
        "#2155cd",
        "#285ccf",
        "#e5efff",
        "#d0defd",
        "#3265d3",
        "#2052cb",
        "#092ba7",
        "#103cbc",
        "#5a8de2",
        "#5f91e3",
        "#3468d4",
        "#78a4eb",
        "#0533b7",
        "#2457ce",
        "#8fb5ee",
        "#2f63d2",
        "#b9d0f8",
        "#c7d6fa",
        "#7ba5ea",
        "#123fbe",
        "#0834b5",
        "#79a5ea",
        "#97baee",
        "#d4e2fe",
        "#c8d8fb",
        "#80aaec",
        "#a0c0f0",
        "#ecf3ff",
        "#e5eeff",
        "#e8efff",
        "#81aaec",
        "#1542c0",
        "#dae5fe",
        "#cbdcfb",
        "#0c38ba",
        "#081d8a",
        "#09289e",
        "#7aa2e8",
        "#5e91e4",
        "#e3edff",
        "#e8f0ff",
        "#dae4fe"
      ],
      "legend_luminance_monotonic": true,
      "n_legend_swatches_ordered": 0
    },
    "phase2": {
      "palette_type": "sequential",
      "confidence": 0.75,
      "details": {
        "n_colors": 117,
        "lightness_range": 79.60032936210136,
        "is_monotonic": false,
        "monotonic_direction": "non-monotonic",
        "is_v_shaped": false,
        "v_midpoint_index": -1,
        "hue_diversity_deg": 10.110431682632488,
        "has_hue_clusters": true,
        "n_achromatic": 43,
        "cluster_info": {
          "cluster1_size": 22,
          "cluster2_size": 68,
          "cluster1_mean_hue": 294.2,
          "cluster2_mean_hue": 275.6,
          "hue_separation": 18.6,
          "max_gap": 326.8
        },
        "avg_chroma": 34.46674742855324,
        "rule": "2b: single_hue_sequential_unordered"
      }
    },
    "phase3": {
      "n_categories": 117,
      "has_numeric_labels": false,
      "has_string_labels": false,
      "usage_distribution": "uniform",
      "has_semantic_midpoint": false,
      "midpoint_type": null,
      "possible_mismatch": false
    },
    "phase4": {
      "needs_user_choice": false,
      "reconciled_type": "sequential",
      "mismatch_explanation": null
    },
    "phase5": {
      "tests_run": [
        {
          "name": "Sequential Test 1: Monotonicity",
          "passed": true,
          "value": 1.0,
          "threshold": 1.0,
          "repair_suggestion": null
        },
        {
          "name": "Sequential Test 2: Uniformity",
          "passed": false,
          "value": 0.93,
          "threshold": 0.8,
          "repair_suggestion": "Redistribute L* evenly (Clip range or resample steps)"
        },
        {
          "name": "Sequential Test 3: Direction",
          "passed": true,
          "value": 1.0,
          "threshold": 1.0,
          "repair_suggestion": null
        },
        {
          "name": "Sequential Test 4: Min Step Size",
          "passed": false,
          "value": 0.0,
          "threshold": 0.28448275862068967,
          "repair_suggestion": "Expand L* range or reduce number of bins"
        }
      ],
      "all_tests_passed": false
    },
    "phase6": {
      "color_mapping": {
        "#0533b7": "#08306b",
        "#092ba7": "#08326e",
        "#0834b5": "#083471",
        "#09289e": "#083674",
        "#081d8a": "#083877",
        "#0c38ba": "#093a79",
        "#103cbc": "#093c7c",
        "#123fbe": "#093e7f",
        "#1542c0": "#094082",
        "#1948c4": "#094285",
        "#1b4bc5": "#094488",
        "#2052cb": "#09468b",
        "#2155cd": "#09488e",
        "#2457ce": "#094a91",
        "#285ccf": "#084c94",
        "#2c5fd1": "#084e97",
        "#2f63d2": "#08509a",
        "#3265d3": "#09529d",
        "#3468d4": "#0b549e",
        "#376bd5": "#0d56a0",
        "#3a6ed6": "#0f57a1",
        "#3c72d7": "#1159a3",
        "#3f76da": "#135ba4",
        "#447bdc": "#145da6",
        "#487fdd": "#165fa7",
        "#4c82de": "#1761a9",
        "#5084df": "#1863aa",
        "#5387e0": "#1a65ac",
        "#578ae1": "#1b67ad",
        "#5a8de2": "#1c69af",
        "#5b8ee2": "#1d6bb0",
        "#5e91e4": "#1f6db2",
        "#5f91e3": "#206fb3",
        "#6293e5": "#2171b5",
        "#6596e6": "#2373b6",
        "#6696e6": "#2675b7",
        "#6999e6": "#2877b8",
        "#6c9ce8": "#2a79b9",
        "#6f9fe9": "#2d7bba",
        "#75a1ea": "#2f7cbb",
        "#77a3ea": "#317ebc",
        "#7aa2e8": "#3380bd",
        "#78a4eb": "#3582be",
        "#77a4ea": "#3684bf",
        "#79a5ea": "#3886c0",
        "#7ba5ea": "#3a88c1",
        "#7aa7ea": "#3c8ac2",
        "#7ea8eb": "#3d8cc3",
        "#80aaec": "#3f8fc4",
        "#81aaec": "#4191c5",
        "#82abec": "#4392c6",
        "#87afed": "#4694c7",
        "#8ab0ed": "#4896c8",
        "#8bb2ed": "#4b97c9",
        "#8fb5ee": "#4e99ca",
        "#90b5ee": "#509bcb",
        "#95b8ef": "#539ccc",
        "#97baee": "#559ecd",
        "#99bbef": "#58a0ce",
        "#9dbef0": "#5aa2cf",
        "#a0c0f0": "#5da3d0",
        "#a1c2f0": "#5fa5d1",
        "#a5c5f1": "#61a7d2",
        "#adc8f5": "#64a8d3",
        "#a9c7f3": "#66aad4",
        "#b0cbf5": "#68acd5",
        "#b2cbf5": "#6aaed6",
        "#b4cdf6": "#6dafd6",
        "#b7cff7": "#71b1d7",
        "#b9d0f8": "#74b3d8",
        "#bbd1f8": "#77b4d8",
        "#bed2f9": "#7bb6d9",
        "#c2d4fa": "#7eb8da",
        "#c3d5fa": "#81b9da",
        "#c6d6fb": "#84bbdb",
        "#c7d6fa": "#87bddc",
        "#c8d8fb": "#8abedc",
        "#c9d8fb": "#8dc0dd",
        "#cad8fb": "#90c2de",
        "#ccdbfc": "#93c3de",
        "#ccdbfb": "#96c5df",
        "#ceddfd": "#99c7e0",
        "#cfddfd": "#9cc9e0",
        "#cbdcfb": "#9ecae1",
        "#d1defe": "#a1cbe2",
        "#d0defd": "#a3cce3",
        "#d3dffe": "#a6cde4",
        "#d5e1ff": "#a8cee4",
        "#d4e2fe": "#abcfe5",
        "#d5e2fe": "#add0e6",
        "#d7e3ff": "#b0d1e7",
        "#dae4ff": "#b2d2e8",
        "#dae4fe": "#b4d3e9",
        "#dae5fe": "#b7d4ea",
        "#dbe6ff": "#b9d5ea",
        "#dce6ff": "#bcd6eb",
        "#dee8ff": "#bed7ec",
        "#e0eaff": "#c0d9ed",
        "#e2ebff": "#c3daee",
        "#e3ecff": "#c5dbef",
        "#e3edff": "#c8dcf0",
        "#e4edff": "#cbdef1",
        "#e5eeff": "#cee0f1",
        "#e5efff": "#d1e2f2",
        "#e6efff": "#d4e4f3",
        "#e8efff": "#d7e6f4",
        "#e8f0ff": "#dae8f5",
        "#e9f0ff": "#ddeaf6",
        "#ebf3ff": "#dfebf7",
        "#ecf3ff": "#e2edf8",
        "#edf5ff": "#e5eff9",
        "#eff6ff": "#e8f1fa",
        "#f1f7ff": "#ebf3fb",
        "#f4faff": "#eef5fc",
        "#f6faff": "#f1f7fd",
        "#f6fbff": "#f4f9fe",
        "#f7fcff": "#f7fbff"
      },
      "new_palette": [
        "#61a7d2",
        "#b2d2e8",
        "#d4e4f3",
        "#9cc9e0",
        "#e5eff9",
        "#6dafd6",
        "#8dc0dd",
        "#dfebf7",
        "#93c3de",
        "#add0e6",
        "#66aad4",
        "#64a8d3",
        "#4392c6",
        "#1d6bb0",
        "#84bbdb",
        "#7eb8da",
        "#539ccc",
        "#f4f9fe",
        "#a1cbe2",
        "#2d7bba",
        "#2a79b9",
        "#3684bf",
        "#2171b5",
        "#0d56a0",
        "#5aa2cf",
        "#1761a9",
        "#bcd6eb",
        "#094285",
        "#1159a3",
        "#4694c7",
        "#71b1d7",
        "#90c2de",
        "#96c5df",
        "#99c7e0",
        "#c0d9ed",
        "#2877b8",
        "#5fa5d1",
        "#3d8cc3",
        "#2373b6",
        "#68acd5",
        "#bed7ec",
        "#ddeaf6",
        "#58a0ce",
        "#77b4d8",
        "#b0d1e7",
        "#c5dbef",
        "#ebf3fb",
        "#eef5fc",
        "#b9d5ea",
        "#e8f1fa",
        "#cbdef1",
        "#a6cde4",
        "#2f7cbb",
        "#4b97c9",
        "#509bcb",
        "#c3daee",
        "#084e97",
        "#1b67ad",
        "#317ebc",
        "#0f57a1",
        "#7bb6d9",
        "#6aaed6",
        "#1863aa",
        "#3c8ac2",
        "#135ba4",
        "#81b9da",
        "#2675b7",
        "#f7fbff",
        "#145da6",
        "#165fa7",
        "#f1f7fd",
        "#4896c8",
        "#a8cee4",
        "#094488",
        "#1a65ac",
        "#09488e",
        "#084c94",
        "#d1e2f2",
        "#a3cce3",
        "#09529d",
        "#09468b",
        "#08326e",
        "#093c7c",
        "#1c69af",
        "#206fb3",
        "#0b549e",
        "#3582be",
        "#08306b",
        "#094a91",
        "#4e99ca",
        "#08509a",
        "#74b3d8",
        "#87bddc",
        "#3a88c1",
        "#093e7f",
        "#083471",
        "#3886c0",
        "#559ecd",
        "#abcfe5",
        "#8abedc",
        "#3f8fc4",
        "#5da3d0",
        "#e2edf8",
        "#cee0f1",
        "#d7e6f4",
        "#4191c5",
        "#094082",
        "#b7d4ea",
        "#9ecae1",
        "#093a79",
        "#083877",
        "#083674",
        "#3380bd",
        "#1f6db2",
        "#c8dcf0",
        "#dae8f5",
        "#b4d3e9"
      ],
      "verification_tests": [
        {
          "name": "Sequential Test 1: Monotonicity",
          "passed": true,
          "value": 1.0
        },
        {
          "name": "Sequential Test 2: Uniformity",
          "passed": true,
          "value": 0.25
        },
        {
          "name": "Sequential Test 3: Direction",
          "passed": true,
          "value": 1.0
        },
        {
          "name": "Sequential Test 4: Min Step Size",
          "passed": true,
          "value": 0.33
        }
      ],
      "verification_passed": true,
      "iterations_used": 1,
      "iteration_log": [
        {
          "iteration": 1,
          "color_mapping": {
            "#0533b7": "#08306b",
            "#092ba7": "#08326e",
            "#0834b5": "#083471",
            "#09289e": "#083674",
            "#081d8a": "#083877",
            "#0c38ba": "#093a79",
            "#103cbc": "#093c7c",
            "#123fbe": "#093e7f",
            "#1542c0": "#094082",
            "#1948c4": "#094285",
            "#1b4bc5": "#094488",
            "#2052cb": "#09468b",
            "#2155cd": "#09488e",
            "#2457ce": "#094a91",
            "#285ccf": "#084c94",
            "#2c5fd1": "#084e97",
            "#2f63d2": "#08509a",
            "#3265d3": "#09529d",
            "#3468d4": "#0b549e",
            "#376bd5": "#0d56a0",
            "#3a6ed6": "#0f57a1",
            "#3c72d7": "#1159a3",
            "#3f76da": "#135ba4",
            "#447bdc": "#145da6",
            "#487fdd": "#165fa7",
            "#4c82de": "#1761a9",
            "#5084df": "#1863aa",
            "#5387e0": "#1a65ac",
            "#578ae1": "#1b67ad",
            "#5a8de2": "#1c69af",
            "#5b8ee2": "#1d6bb0",
            "#5e91e4": "#1f6db2",
            "#5f91e3": "#206fb3",
            "#6293e5": "#2171b5",
            "#6596e6": "#2373b6",
            "#6696e6": "#2675b7",
            "#6999e6": "#2877b8",
            "#6c9ce8": "#2a79b9",
            "#6f9fe9": "#2d7bba",
            "#75a1ea": "#2f7cbb",
            "#77a3ea": "#317ebc",
            "#7aa2e8": "#3380bd",
            "#78a4eb": "#3582be",
            "#77a4ea": "#3684bf",
            "#79a5ea": "#3886c0",
            "#7ba5ea": "#3a88c1",
            "#7aa7ea": "#3c8ac2",
            "#7ea8eb": "#3d8cc3",
            "#80aaec": "#3f8fc4",
            "#81aaec": "#4191c5",
            "#82abec": "#4392c6",
            "#87afed": "#4694c7",
            "#8ab0ed": "#4896c8",
            "#8bb2ed": "#4b97c9",
            "#8fb5ee": "#4e99ca",
            "#90b5ee": "#509bcb",
            "#95b8ef": "#539ccc",
            "#97baee": "#559ecd",
            "#99bbef": "#58a0ce",
            "#9dbef0": "#5aa2cf",
            "#a0c0f0": "#5da3d0",
            "#a1c2f0": "#5fa5d1",
            "#a5c5f1": "#61a7d2",
            "#adc8f5": "#64a8d3",
            "#a9c7f3": "#66aad4",
            "#b0cbf5": "#68acd5",
            "#b2cbf5": "#6aaed6",
            "#b4cdf6": "#6dafd6",
            "#b7cff7": "#71b1d7",
            "#b9d0f8": "#74b3d8",
            "#bbd1f8": "#77b4d8",
            "#bed2f9": "#7bb6d9",
            "#c2d4fa": "#7eb8da",
            "#c3d5fa": "#81b9da",
            "#c6d6fb": "#84bbdb",
            "#c7d6fa": "#87bddc",
            "#c8d8fb": "#8abedc",
            "#c9d8fb": "#8dc0dd",
            "#cad8fb": "#90c2de",
            "#ccdbfc": "#93c3de",
            "#ccdbfb": "#96c5df",
            "#ceddfd": "#99c7e0",
            "#cfddfd": "#9cc9e0",
            "#cbdcfb": "#9ecae1",
            "#d1defe": "#a1cbe2",
            "#d0defd": "#a3cce3",
            "#d3dffe": "#a6cde4",
            "#d5e1ff": "#a8cee4",
            "#d4e2fe": "#abcfe5",
            "#d5e2fe": "#add0e6",
            "#d7e3ff": "#b0d1e7",
            "#dae4ff": "#b2d2e8",
            "#dae4fe": "#b4d3e9",
            "#dae5fe": "#b7d4ea",
            "#dbe6ff": "#b9d5ea",
            "#dce6ff": "#bcd6eb",
            "#dee8ff": "#bed7ec",
            "#e0eaff": "#c0d9ed",
            "#e2ebff": "#c3daee",
            "#e3ecff": "#c5dbef",
            "#e3edff": "#c8dcf0",
            "#e4edff": "#cbdef1",
            "#e5eeff": "#cee0f1",
            "#e5efff": "#d1e2f2",
            "#e6efff": "#d4e4f3",
            "#e8efff": "#d7e6f4",
            "#e8f0ff": "#dae8f5",
            "#e9f0ff": "#ddeaf6",
            "#ebf3ff": "#dfebf7",
            "#ecf3ff": "#e2edf8",
            "#edf5ff": "#e5eff9",
            "#eff6ff": "#e8f1fa",
            "#f1f7ff": "#ebf3fb",
            "#f4faff": "#eef5fc",
            "#f6faff": "#f1f7fd",
            "#f6fbff": "#f4f9fe",
            "#f7fcff": "#f7fbff"
          },
          "verification_passed": true,
          "tests": [
            {
              "name": "Sequential Test 1: Monotonicity",
              "passed": true,
              "value": 1.0
            },
            {
              "name": "Sequential Test 2: Uniformity",
              "passed": true,
              "value": 0.25
            },
            {
              "name": "Sequential Test 3: Direction",
              "passed": true,
              "value": 1.0
            },
            {
              "name": "Sequential Test 4: Min Step Size",
              "passed": true,
              "value": 0.33
            }
          ]
        }
      ]
    }
  },
  "warnings": [],
  "recoloring_applied": true,
  "processing_time_sec": 6.395
}